LICENSE.txt
MANIFEST.in
distribute_setup.py
setup.py
.hg/cur-message.txt
.hg/last-message.txt
ezcomet/__init__.py
ezcomet/cacerts.txt
ezcomet.egg-info/PKG-INFO
ezcomet.egg-info/SOURCES.txt
ezcomet.egg-info/dependency_links.txt
ezcomet.egg-info/entry_points.txt
ezcomet.egg-info/not-zip-safe
ezcomet.egg-info/requires.txt
ezcomet.egg-info/top_level.txt