Metadata-Version: 1.0
Name: ezcomet
Version: 0.2
Summary: The Python API of EZComet.com Ajax/Comet service
Home-page: http://ezcomet.com/tools/python_sdk
Author: EZComet.com
Author-email: bornstub@gmail.com
License: MIT
Platform: UNKNOWN
